oneneuron/__init__.py
oneneuron/perceptron.py
Pypi_bhushanasati25-0.0.2.dist-info/LICENSE
Pypi_bhushanasati25-0.0.2.dist-info/METADATA
Pypi_bhushanasati25-0.0.2.dist-info/WHEEL
Pypi_bhushanasati25-0.0.2.dist-info/top_level.txt
Pypi_bhushanasati25-0.0.2.dist-info/RECORD
